[
  {
    "id": "ebdb20e6",
    "content": "c21",
    "type": "t",
    "importance": 0.5,
    "tags": [
      "t"
    ],
    "state": "working",
    "created_tick": 0,
    "last_access_tick": 0,
    "last_state_change_tick": 0,
    "access_count": 0,
    "access_history": [],
    "activation_count": 0,
    "decay_buffer_entry_tick": null,
    "promotion_history": [],
    "demotion_history": [],
    "compressed_from": null,
    "compression_count": 0,
    "goal_relevance": 0.0
  },
  {
    "id": "24347cbf",
    "content": "c22",
    "type": "t",
    "importance": 0.5,
    "tags": [
      "t"
    ],
    "state": "working",
    "created_tick": 0,
    "last_access_tick": 0,
    "last_state_change_tick": 0,
    "access_count": 0,
    "access_history": [],
    "activation_count": 0,
    "decay_buffer_entry_tick": null,
    "promotion_history": [],
    "demotion_history": [],
    "compressed_from": null,
    "compression_count": 0,
    "goal_relevance": 0.0
  },
  {
    "id": "f8b75345",
    "content": "c23",
    "type": "t",
    "importance": 0.5,
    "tags": [
      "t"
    ],
    "state": "working",
    "created_tick": 0,
    "last_access_tick": 0,
    "last_state_change_tick": 0,
    "access_count": 0,
    "access_history": [],
    "activation_count": 0,
    "decay_buffer_entry_tick": null,
    "promotion_history": [],
    "demotion_history": [],
    "compressed_from": null,
    "compression_count": 0,
    "goal_relevance": 0.0
  },
  {
    "id": "ac613d6e",
    "content": "c24",
    "type": "t",
    "importance": 0.5,
    "tags": [
      "t"
    ],
    "state": "working",
    "created_tick": 0,
    "last_access_tick": 0,
    "last_state_change_tick": 0,
    "access_count": 0,
    "access_history": [],
    "activation_count": 0,
    "decay_buffer_entry_tick": null,
    "promotion_history": [],
    "demotion_history": [],
    "compressed_from": null,
    "compression_count": 0,
    "goal_relevance": 0.0
  },
  {
    "id": "288fa666",
    "content": "c25",
    "type": "t",
    "importance": 0.5,
    "tags": [
      "t"
    ],
    "state": "working",
    "created_tick": 0,
    "last_access_tick": 0,
    "last_state_change_tick": 0,
    "access_count": 0,
    "access_history": [],
    "activation_count": 0,
    "decay_buffer_entry_tick": null,
    "promotion_history": [],
    "demotion_history": [],
    "compressed_from": null,
    "compression_count": 0,
    "goal_relevance": 0.0
  },
  {
    "id": "6c6af615",
    "content": "c26",
    "type": "t",
    "importance": 0.5,
    "tags": [
      "t"
    ],
    "state": "working",
    "created_tick": 0,
    "last_access_tick": 0,
    "last_state_change_tick": 0,
    "access_count": 0,
    "access_history": [],
    "activation_count": 0,
    "decay_buffer_entry_tick": null,
    "promotion_history": [],
    "demotion_history": [],
    "compressed_from": null,
    "compression_count": 0,
    "goal_relevance": 0.0
  },
  {
    "id": "084a9ed7",
    "content": "c27",
    "type": "t",
    "importance": 0.5,
    "tags": [
      "t"
    ],
    "state": "working",
    "created_tick": 0,
    "last_access_tick": 0,
    "last_state_change_tick": 0,
    "access_count": 0,
    "access_history": [],
    "activation_count": 0,
    "decay_buffer_entry_tick": null,
    "promotion_history": [],
    "demotion_history": [],
    "compressed_from": null,
    "compression_count": 0,
    "goal_relevance": 0.0
  },
  {
    "id": "17138839",
    "content": "c28",
    "type": "t",
    "importance": 0.5,
    "tags": [
      "t"
    ],
    "state": "working",
    "created_tick": 0,
    "last_access_tick": 0,
    "last_state_change_tick": 0,
    "access_count": 0,
    "access_history": [],
    "activation_count": 0,
    "decay_buffer_entry_tick": null,
    "promotion_history": [],
    "demotion_history": [],
    "compressed_from": null,
    "compression_count": 0,
    "goal_relevance": 0.0
  },
  {
    "id": "324a05c1",
    "content": "c29",
    "type": "t",
    "importance": 0.5,
    "tags": [
      "t"
    ],
    "state": "working",
    "created_tick": 0,
    "last_access_tick": 0,
    "last_state_change_tick": 0,
    "access_count": 0,
    "access_history": [],
    "activation_count": 0,
    "decay_buffer_entry_tick": null,
    "promotion_history": [],
    "demotion_history": [],
    "compressed_from": null,
    "compression_count": 0,
    "goal_relevance": 0.0
  },
  {
    "id": "301fb76c",
    "content": "c30",
    "type": "t",
    "importance": 0.5,
    "tags": [
      "t"
    ],
    "state": "working",
    "created_tick": 0,
    "last_access_tick": 0,
    "last_state_change_tick": 0,
    "access_count": 0,
    "access_history": [],
    "activation_count": 0,
    "decay_buffer_entry_tick": null,
    "promotion_history": [],
    "demotion_history": [],
    "compressed_from": null,
    "compression_count": 0,
    "goal_relevance": 0.0
  }
]